{
    "title": "Muuyu and ThinkPad Edge Take Yoga Digital",
    "description": "Matt Devine--yoga teacher and founder of Muuyu, one of the world's first online interactive eYoga platforms--describes how Muuyu and a ThinkPad Edge PC with the latest Intel Core processors are enabling yoga teachers and students to virtually practice yoga from any location.",
    "referenceId": "ho32aF1XUug",
    "date_created": "1291391381",
    "date_modified": "1494959645",
    "tags": "",
    "sourceId": "4",
    "VIDEO_LENGTH": "SHORT",
    "duration": "88",
    "status": "pending",
    "visibility": "1",
    "VV_VI": null,
    "CVV_VI": null,
    "engagement_score": null,
    "conversion_score": null,
    "id": "91834287",
    "loginId": "1758939",
    "entityType": "1",
    "sortOrder": "5",
    "entityIdParent": "91834481",
    "titleTextEncoded": "Muuyu-and-ThinkPad-Edge-Take-Yoga-Digital",
    "category": "",
    "settings": "",
    "asset": {
        "type": "youtube",
        "thumbnailUrl": "https:\/\/i.ytimg.com\/vi\/ho32aF1XUug\/hqdefault.jpg",
        "uploadDate": 1291391381,
        "videoId": "ho32aF1XUug",
        "title": "Muuyu and ThinkPad Edge Take Yoga Digital",
        "description": "Matt Devine--yoga teacher and founder of Muuyu, one of the world's first online interactive eYoga platforms--describes how Muuyu and a ThinkPad Edge PC with the latest Intel Core processors are enabling yoga teachers and students to virtually practice yoga from any location.",
        "author": "Lenovo",
        "mediaDuration": 88,
        "prettyDuration": "00:01:28",
        "views": "3400"
    },
    "transcripts": "",
    "metrics_statistics": null,
    "tvp_profiles": null,
    "tvp_profiles_manual": null,
    "tvp_profiles_maxscore": null
}